dimits/__init__.py
dimits/main.py
dimits/ttsmodel.py
dimits/utils.py
dimits-0.0.31a0.dist-info/LICENSE
dimits-0.0.31a0.dist-info/METADATA
dimits-0.0.31a0.dist-info/WHEEL
dimits-0.0.31a0.dist-info/RECORD
