Metadata-Version: 2.1
Name: dimits
Version: 0.0.31a0
Summary: Dimits is a Python library that provides an easy-to-use interface to the Piper text-to-speech (TTS) system. It utilizes the powerful Piper TTS engine, which is optimized for Raspberry Pi 4, to generate high-quality synthesized speech.
License: MIT
Author: Reqeique
Author-email: ananiyajemberu21@gmail.com
Requires-Python: >=3.9,<4.0
Classifier: License :: OSI Approved :: MIT License
Classifier: Programming Language :: Python :: 3
Classifier: Programming Language :: Python :: 3.9
Classifier: Programming Language :: Python :: 3.10
Classifier: Programming Language :: Python :: 3.11
Classifier: Programming Language :: Python :: 3.12
Requires-Dist: espeak-phonemizer
Requires-Dist: espeak-phonemizer-windows ; sys_platform == "win32"
Requires-Dist: huggingface-hub (==0.23.0)
Requires-Dist: onnxruntime
Requires-Dist: requests (>=2.13.0,<3.0.0)
Requires-Dist: soundfile
Requires-Dist: tqdm (==4.64.0)
